[
  {
    "title": "ยิหวาดาตัง ep 7",
    "traffic_num": 500,
    "pub_date": "2026-02-02T07:40:00-08:00",
    "picture": "https://encrypted-tbn3.gstatic.com/images?q=tbn:ANd9GcQVsISUOTVHOtH_rrYdpmBCZMf4hv0cdTiAlOTv1JISu7dhSXqyWA5MdcgIGow",
    "news": [
      {
        "title": "เรื่องย่อ ยิหวาดาตัง EP.7 เยี่ยม รอดตาย สาบานล้างแค้นเสือผุด",
        "url": "https://www.sanook.com/movie/187190/",
        "source": "Sanook",
        "picture": "https://encrypted-tbn3.gstatic.com/images?q=tbn:ANd9GcQVsISUOTVHOtH_rrYdpmBCZMf4hv0cdTiAlOTv1JISu7dhSXqyWA5MdcgIGow"
      },
      {
        "title": "ชวนดูละครไทย ยิหวาดาตัง ไสยเวท–บาป–โศกนาฏกรรม",
        "url": "https://entertainment.trueid.net/detail/xnBMmV96xBwP",
        "source": "TrueID",
        "picture": "https://encrypted-tbn0.gstatic.com/images?q=tbn:ANd9GcTV0eoVNxW1lVJBwqTl_VqgHTH7nA3gEOSZeSCBziClFC3e9z39ZM1cYtwTPU0"
      },
      {
        "title": "“ป๋อ ณัฐวุฒิ” ผนึกกำลัง “ตี๋ ดอกสะเดา” โชว์ลีลาบู๊ปกป้องชุมเสือ",
        "url": "https://mgronline.com/drama/detail/9690000010242",
        "source": "ผู้จัดการออนไลน์",
        "picture": "https://encrypted-tbn0.gstatic.com/images?q=tbn:ANd9GcSKUgQKnu2pEwqguV7vgrSHl6h-iTV53mln7IN9TwOIlib7s0IzMrpJvUWcKpk"
      }
    ],
    "regions": [
      "Thailand(all region)"
    ],
    "country": "Thailand"
  },
  {
    "title": "อัลนาสเซอร์",
    "traffic_num": 100,
    "pub_date": "2026-02-02T07:40:00-08:00",
    "picture": "https://encrypted-tbn0.gstatic.com/images?q=tbn:ANd9GcRfLGQ8nMN0FwlmbGPyb6TFKg6tJBJ1EjF0GIgQjDL5ble1ZByexlZ4Xjtzu5k",
    "news": [
      {
        "title": "แม้อยู่คนละสโมสร โรนัลโด โดดขวาง เบนเซมา ย้ายทีมไปอยู่ อัล ฮิลัล",
        "url": "https://www.khaosod.co.th/sports/news_10122775",
        "source": "ข่าวสด",
        "picture": "https://encrypted-tbn0.gstatic.com/images?q=tbn:ANd9GcRfLGQ8nMN0FwlmbGPyb6TFKg6tJBJ1EjF0GIgQjDL5ble1ZByexlZ4Xjtzu5k"
      },
      {
        "title": "ไปMLS?! โหม 'โด้' แตกหักอัล-นาสเซอร์ | Soccersuck",
        "url": "https://today.line.me/th/v3/article/8nq0pmM",
        "source": "LINE TODAY",
        "picture": "https://encrypted-tbn2.gstatic.com/images?q=tbn:ANd9GcQoIaRp6IwS52dIPXeE8x3F8S6VDHhIs-_RBa8QdjX7SGtnrcFT69hPJ8Uas0o"
      },
      {
        "title": "ทีมของโรนัลโด้กำลังเงินหมดสำหรับการซื้อตัวผู้เล่นหรือเปล่า?",
        "url": "https://www.vietnam.vn/th/doi-cua-ronaldo-can-tien-mua-sam",
        "source": "Vietnam.vn",
        "picture": "https://encrypted-tbn1.gstatic.com/images?q=tbn:ANd9GcRRIArM6wLhqFC4-M_6OyDeyu0z8y_4QgN1G_-JH-sQMxllYdnj8dqbgIHn4bk"
      }
    ],
    "regions": [
      "Thailand(all region)"
    ],
    "country": "Thailand"
  },
  {
    "title": "al-riyadh vs al-nassr",
    "traffic_num": 200,
    "pub_date": "2026-02-02T07:20:00-08:00",
    "picture": "https://encrypted-tbn0.gstatic.com/images?q=tbn:ANd9GcQeu7Pbngu6H6AeJYz8LKKjCe9UyFkc5HsigfbfNakTD5UjDNX2CBRI1KSJMwU",
    "news": [
      {
        "title": "Cristiano Ronaldo: ‘Betrayed’ Man Utd legend ‘could leave’ and return to Europe on deadline day",
        "url": "https://www.football365.com/news/cristiano-ronaldo-betrayed-man-utd-legend-leave-saudi-arabia-european-return-deadline-day",
        "source": "Football365",
        "picture": "https://encrypted-tbn0.gstatic.com/images?q=tbn:ANd9GcQeu7Pbngu6H6AeJYz8LKKjCe9UyFkc5HsigfbfNakTD5UjDNX2CBRI1KSJMwU"
      },
      {
        "title": "Ronaldo sits out for Al-Nassr amid tension with PIF ownership",
        "url": "https://www.cbssports.com/soccer/news/cristiano-ronaldo-frustrations-with-saudis-pif-ownership-lead-to-star-striker-missing-al-nassr-lineup/",
        "source": "CBS Sports",
        "picture": "https://encrypted-tbn3.gstatic.com/images?q=tbn:ANd9GcQcmGClnhFvvBBCgo7-DZ3goCL88VSgFgRo38gRU6dP9gEzFvHQaton5vrTIDA"
      },
      {
        "title": "What is going on with Ronaldo in Saudi Arabia?",
        "url": "https://sports.yahoo.com/articles/going-ronaldo-saudi-arabia-154703859.html",
        "source": "Yahoo Sports",
        "picture": "https://encrypted-tbn0.gstatic.com/images?q=tbn:ANd9GcS38YIXxpkadnSpsI44QNjFi9EOeEhvFJBOnULmq-23udEzZ6dRO3gHkTjI0is"
      }
    ],
    "regions": [
      "Thailand(all region)"
    ],
    "country": "Thailand"
  },
  {
    "title": "ธนาธร",
    "traffic_num": 100,
    "pub_date": "2026-02-02T07:10:00-08:00",
    "picture": "https://encrypted-tbn0.gstatic.com/images?q=tbn:ANd9GcSr41eJR1QqDhTtjYOHNkBTq6VsjrNKZXwdicxkhaiPPjGncXZSXYvr32p-X_s",
    "news": [
      {
        "title": "ปชน. ดาวกระจายปราศรัย “พิธา” ไปสกล “ธนาธร” อยู่สระแก้ว แฉมีคนจ้องทำลายพรรคส้ม",
        "url": "https://www.thairath.co.th/news/politic/2911348",
        "source": "Thairath.co.th",
        "picture": "https://encrypted-tbn0.gstatic.com/images?q=tbn:ANd9GcSr41eJR1QqDhTtjYOHNkBTq6VsjrNKZXwdicxkhaiPPjGncXZSXYvr32p-X_s"
      },
      {
        "title": "เปิดแผนแก้เกมศึกชิงตั้งรัฐบาล | 31 ม.ค. 69",
        "url": "https://www.thaipbs.or.th/program/KaoJoh/episodes/112882",
        "source": "Thai PBS",
        "picture": "https://encrypted-tbn2.gstatic.com/images?q=tbn:ANd9GcR5M6-ThNafWXngw1cvSac4s0a4KFp2djShvoIW9wS5OAX4pijiAVZOrmJQfFE"
      },
      {
        "title": "เลือกตั้ง 2569 : \"ธนาธร\" ขอพี่น้องอย่าหมดหวัง กาประชาชนส่ง \"ณัฐพงษ์\" นั่งนายกฯ",
        "url": "https://www.pptvhd36.com/news/%E0%B8%81%E0%B8%B2%E0%B8%A3%E0%B9%80%E0%B8%A1%E0%B8%B7%E0%B8%AD%E0%B8%87/267373",
        "source": "pptvhd36",
        "picture": "https://encrypted-tbn2.gstatic.com/images?q=tbn:ANd9GcSu1GVAKDGCIGMNbcCFRtsohdKUo5K1zxH4hyGg66xRueTTjtbt9icXL3jMwGk"
      }
    ],
    "regions": [
      "Thailand(all region)"
    ],
    "country": "Thailand"
  },
  {
    "title": "the wrecking crew",
    "traffic_num": 100,
    "pub_date": "2026-02-02T06:30:00-08:00",
    "picture": "https://encrypted-tbn2.gstatic.com/images?q=tbn:ANd9GcSNiBQjdzy1CLfOIRBvBTsWlHSn9rDMND3zJcMqHCYSVBtjY8x7NZe4a1gel6g",
    "news": [
      {
        "title": "‘The Wrecking Crew’ Review: Jason Momoa and Dave Bautista Play Estranged Half-Bros With ‘Issues’",
        "url": "https://variety.com/2026/film/reviews/the-wrecking-crew-review-jason-momoa-dave-bautista-1236640685/",
        "source": "Variety",
        "picture": "https://encrypted-tbn2.gstatic.com/images?q=tbn:ANd9GcSNiBQjdzy1CLfOIRBvBTsWlHSn9rDMND3zJcMqHCYSVBtjY8x7NZe4a1gel6g"
      },
      {
        "title": "Prime Video’s New #1 Movie Finally Brings Back An Iconic Genre",
        "url": "https://screenrant.com/prime-videos-new-1-movie-finally-brings-back-an-iconic-genre/",
        "source": "Screen Rant",
        "picture": "https://encrypted-tbn1.gstatic.com/images?q=tbn:ANd9GcSbNSbavm7IpaYxrujZ_HdTM0lBP4zXpntmGBKVqBb7iicRMPDSCrZY-yDYPSM"
      },
      {
        "title": "Wreaking Havoc with the Cast and Director of ‘The Wrecking Crew’",
        "url": "https://thenerdsofcolor.org/2026/01/30/wreaking-havoc-with-the-cast-and-director-of-the-wrecking-crew/",
        "source": "The Nerds of Color",
        "picture": "https://encrypted-tbn0.gstatic.com/images?q=tbn:ANd9GcRXVHv_9S5-Z7ovwEXlw3Fca6d47I7kGGfebtdGhSuHh-zqHrAw4sbEAenaFbs"
      }
    ],
    "regions": [
      "Thailand(all region)"
    ],
    "country": "Thailand"
  },
  {
    "title": "ซันเดอร์แลนด์",
    "traffic_num": 1000,
    "pub_date": "2026-02-02T05:50:00-08:00",
    "picture": "https://encrypted-tbn3.gstatic.com/images?q=tbn:ANd9GcQKiqjrpu8x-imYaL8mzPTWK0IOMkbWDioju8ivgQnGeKz8OWXVqI9Y5dNiZ6I",
    "news": [
      {
        "title": "ชี้ 4 ตัวเต็งบอลน่าเชียร์ 2 ก.พ. 69 : ทีเด็ดบอลวันนี้ เบิร์นลี่ย์มีแต้ม, โรม่าเดินหน้าคว้าชัย",
        "url": "https://www.siamsport.co.th/football-international/premierleague/99359/",
        "source": "Siamsport",
        "picture": "https://encrypted-tbn3.gstatic.com/images?q=tbn:ANd9GcQKiqjrpu8x-imYaL8mzPTWK0IOMkbWDioju8ivgQnGeKz8OWXVqI9Y5dNiZ6I"
      },
      {
        "title": "ทีเด็ดบอลวันนี้ 2 ก.พ. 69 วิเคราะห์บอล 3 ตัวเต็ง เปิดโปรแกรมบอลวันนี้ ลุ้น 3 ลีกใหญ่",
        "url": "https://www.thairath.co.th/sport/eurofootball/premierleague/2911450",
        "source": "Thairath",
        "picture": "https://encrypted-tbn1.gstatic.com/images?q=tbn:ANd9GcS9BvJv152ZW8BBc8_UpborK-BpQTY8Z_uyJ51lsixwbvTMDg9CmddcS2V-FU8"
      },
      {
        "title": "โปรแกรมกีฬาวันนี้ พร้อมช่องถ่ายทอดสด วันจันทร์ที่ 2 กุมภาพันธ์ 2569",
        "url": "https://www.tnnthailand.com/sports/224362/",
        "source": "TNN",
        "picture": "https://encrypted-tbn2.gstatic.com/images?q=tbn:ANd9GcT3T-OvQUVax_MYPR_8sC75cDQWpX63kUqqGaHVcCHxz41ybyejDoASatrs9YQ"
      }
    ],
    "regions": [
      "Thailand(all region)"
    ],
    "country": "Thailand"
  },
  {
    "title": "หวยลาว2/2/69",
    "traffic_num": 50000,
    "pub_date": "2026-02-02T05:20:00-08:00",
    "picture": "https://encrypted-tbn0.gstatic.com/images?q=tbn:ANd9GcQRHLG8Xw-_aH0U_neY2nwuGLGlc16ymfg2VYUe-1iJlW4ecFV31XQOx_2OPEA",
    "news": [
      {
        "title": "หวยลาววันนี้ 2 กุมภาพันธ์ 2569 ตรวจผลหวยลาว หวยลาววันนี้ออกอะไร?",
        "url": "https://www.sanook.com/news/9871462/",
        "source": "Sanook",
        "picture": "https://encrypted-tbn0.gstatic.com/images?q=tbn:ANd9GcQRHLG8Xw-_aH0U_neY2nwuGLGlc16ymfg2VYUe-1iJlW4ecFV31XQOx_2OPEA"
      },
      {
        "title": "หวยลาววันนี้ 30 มกราคม 2569 ตรวจผลหวยลาว หวยลาววันนี้ออกอะไร?",
        "url": "https://www.sanook.com/news/9870946/",
        "source": "Sanook",
        "picture": "https://encrypted-tbn2.gstatic.com/images?q=tbn:ANd9GcRqR2wWGiW5CFY7rsveNBJdWB1eZHWZ5egglV0IAXVvxyzvpzjHwGslt_qbGKw"
      },
      {
        "title": "หวยลาววันนี้ งวดประจำวันที่ 26 มกราคม 2569 ผลหวยพัฒนาล่าสุด ตรวจรางวัล หวยลาว ออกอะไร",
        "url": "https://www.khaosod.co.th/laolottery/news_10112901",
        "source": "ข่าวสด",
        "picture": "https://encrypted-tbn0.gstatic.com/images?q=tbn:ANd9GcStdhVFNpPolboDHXMvEYqNrlxay9Q8KLRMBtl1AkZbM7a0kXMtF8NIhjkvKp0"
      }
    ],
    "regions": [
      "Thailand(all region)"
    ],
    "country": "Thailand"
  },
  {
    "title": "ดวงจันทร์",
    "traffic_num": 200,
    "pub_date": "2026-02-02T04:40:00-08:00",
    "picture": "https://encrypted-tbn2.gstatic.com/images?q=tbn:ANd9GcSuzoOKrNr8h3OrwW_hU6MxW6ZOcDvLg0j180IIR30BuIPdls5ErGKG0AjTuYo",
    "news": [
      {
        "title": "“NASA” ซ้อมเติมเชื้อเพลิง “Artemis 2” เตรียมส่งมนุษย์กลับไปเยือนดวงจันทร์",
        "url": "https://www.tnnthailand.com/tech/224457/",
        "source": "TNN",
        "picture": "https://encrypted-tbn2.gstatic.com/images?q=tbn:ANd9GcSuzoOKrNr8h3OrwW_hU6MxW6ZOcDvLg0j180IIR30BuIPdls5ErGKG0AjTuYo"
      },
      {
        "title": "นาซ่าเริ่มซ้อมรบสำหรับการลงจอดบนดวงจันทร์ครั้งแรกในรอบกว่า 50 ปี",
        "url": "https://www.vietnam.vn/th/nasa-bat-dau-tong-duyet-chuyen-bay-dau-tien-dua-nguoi-len-mat-trang-sau-hon-50-nam",
        "source": "Vietnam.vn",
        "picture": "https://encrypted-tbn1.gstatic.com/images?q=tbn:ANd9GcTlku-nz2Q6qU0HcXwnmy2V06PmzeiBPTQ_NJve901GHwKs9PEaml5sY3OVJjY"
      },
      {
        "title": "ภารกิจสำรวจดวงจันทร์ \"อาร์ทิมิส 2\" จะเริ่มต้นเมื่อใด ใครร่วมภารกิจบ้าง",
        "url": "https://www.bbc.com/thai/articles/cvgjr54mj92o",
        "source": "BBC",
        "picture": "https://encrypted-tbn0.gstatic.com/images?q=tbn:ANd9GcT0Pc2ufwNnwohejXWMuNwCZ9pHGMFiadkYe6NszFwI3NxkWBeCgJKFA9Y8XF0"
      }
    ],
    "regions": [
      "Thailand(all region)"
    ],
    "country": "Thailand"
  },
  {
    "title": "มายอร์ก้า",
    "traffic_num": 500,
    "pub_date": "2026-02-02T04:20:00-08:00",
    "picture": "https://encrypted-tbn2.gstatic.com/images?q=tbn:ANd9GcSt08Fkor8lVLnQF70BNKMIxLMWUAB_QKF5XBRjG9i1xQf8TBx9LYo1TMyEnug",
    "news": [
      {
        "title": "Preview: Mallorca vs Sevilla - prediction, team news, lineups",
        "url": "https://www.sportsmole.co.uk/football/mallorca/preview/mallorca-vs-sevilla-prediction-team-news-lineups_591102.html",
        "source": "Sports Mole",
        "picture": "https://encrypted-tbn2.gstatic.com/images?q=tbn:ANd9GcSt08Fkor8lVLnQF70BNKMIxLMWUAB_QKF5XBRjG9i1xQf8TBx9LYo1TMyEnug"
      },
      {
        "title": "Mallorca vs. Sevilla: La Liga betting odds, prediction, pick",
        "url": "https://www.usatoday.com/story/sports/soccer/2026/02/02/mallorca-vs-sevilla-la-liga-betting-odds-prediction-pick/88469867007/",
        "source": "USA Today",
        "picture": "https://encrypted-tbn1.gstatic.com/images?q=tbn:ANd9GcTs13Kp-gOUVeoW-vaDSY8Sjka3wXTcEHKVH5ywRHppTp9doDaAq871-M3056Q"
      },
      {
        "title": "Real Mallorca vs Sevilla Prediction: Sevilla to win on the road",
        "url": "https://insights.betfred.com/football/la-liga/mallorca-vs-sevilla-prediction-betting-tips-odds-020226/",
        "source": "Betfred Insights",
        "picture": "https://encrypted-tbn0.gstatic.com/images?q=tbn:ANd9GcRRK77dvXKsLJVPz4SvesOQ-F7v11rc8Dme8EZqztK1o5p63CQKkwNq01lm_Wk"
      }
    ],
    "regions": [
      "Thailand(all region)"
    ],
    "country": "Thailand"
  },
  {
    "title": "จันทร์ซ้อนจันทร์ปี 2569",
    "traffic_num": 1000,
    "pub_date": "2026-02-02T03:50:00-08:00",
    "picture": "https://encrypted-tbn0.gstatic.com/images?q=tbn:ANd9GcRFuvY3WwOdgUetypPHKv5gL1jX2An6_3l1FinpWon67NbQquQKgmglVyk2kCM",
    "news": [
      {
        "title": "คืนนี้ จันทร์ซ้อนจันทร์ ครั้งแรกของปี 2569 โหรรัตนโกสินทร์ เปิดฤกษ์เศรษฐี",
        "url": "https://www.siamnews.com/lifestyle/belief/37732",
        "source": "SiamNews",
        "picture": "https://encrypted-tbn0.gstatic.com/images?q=tbn:ANd9GcRFuvY3WwOdgUetypPHKv5gL1jX2An6_3l1FinpWon67NbQquQKgmglVyk2kCM"
      },
      {
        "title": "เปิดดวงการเงิน",
        "url": "https://postjung.com/tag/%E0%B9%80%E0%B8%9B%E0%B8%B4%E0%B8%94%E0%B8%94%E0%B8%A7%E0%B8%87%E0%B8%81%E0%B8%B2%E0%B8%A3%E0%B9%80%E0%B8%87%E0%B8%B4%E0%B8%99",
        "source": "Postjung",
        "picture": "https://encrypted-tbn2.gstatic.com/images?q=tbn:ANd9GcQ7G7d5O9Kry4iJOfmzR9Ycpnf1kDf3LRFyBYO4A4aalCjYvawPBq6TlXa28EQ"
      }
    ],
    "regions": [
      "Thailand(all region)"
    ],
    "country": "Thailand"
  }
]